[
    {
        "id": 0,
        "title": "Song 1",
        "notes": []
    },
    {
        "title": "Song Number 2",
        "notes": [
            {
                "lyrics": "What",
                "duration": "8",
                "notes": [
                    7
                ]
            },
            {
                "lyrics": "child",
                "duration": "16",
                "notes": [
                    10
                ]
            },
            {
                "lyrics": "is",
                "duration": "8",
                "notes": [
                    12
                ]
            },
            {
                "lyrics": "this",
                "duration": "12",
                "notes": [
                    14
                ]
            },
            {
                "lyrics": "",
                "duration": "4",
                "notes": [
                    16
                ]
            },
            {
                "lyrics": "",
                "duration": -1,
                "notes": []
            },
            {
                "lyrics": "who",
                "duration": "4",
                "notes": [
                    14
                ]
            },
            {
                "lyrics": "laid",
                "duration": "16",
                "notes": [
                    12
                ]
            },
            {
                "lyrics": "to",
                "duration": "8",
                "notes": [
                    9
                ]
            },
            {
                "lyrics": "rest",
                "duration": "12",
                "notes": [
                    5
                ]
            },
            {
                "lyrics": "",
                "duration": "4",
                "notes": [
                    7
                ]
            },
            {
                "lyrics": "",
                "duration": -1,
                "notes": []
            },
            {
                "lyrics": "on",
                "duration": "4",
                "notes": [
                    9
                ]
            },
            {
                "lyrics": "Mary's",
                "duration": "16",
                "notes": [
                    10
                ]
            },
            {
                "lyrics": "",
                "duration": "8",
                "notes": [
                    7
                ]
            },
            {
                "lyrics": "lap",
                "duration": "12",
                "notes": [
                    7
                ]
            },
            {
                "lyrics": "is",
                "duration": "4",
                "notes": [
                    6
                ]
            },
            {
                "lyrics": "",
                "duration": "4",
                "notes": [
                    7
                ]
            },
            {
                "lyrics": "sleeping?",
                "duration": "12",
                "notes": [
                    9
                ]
            },
            {
                "lyrics": "",
                "duration": "8",
                "notes": [
                    6
                ]
            },
            {
                "lyrics": "",
                "duration": "16",
                "notes": [
                    2
                ]
            },
            {
                "lyrics": "",
                "duration": -1,
                "notes": []
            },
            {
                "lyrics": "Whom",
                "duration": "8",
                "notes": [
                    7
                ]
            },
            {
                "lyrics": "angels",
                "duration": "16",
                "notes": [
                    10
                ]
            },
            {
                "lyrics": "",
                "duration": "8",
                "notes": [
                    12
                ]
            },
            {
                "lyrics": "greet",
                "duration": "12",
                "notes": [
                    14
                ]
            },
            {
                "lyrics": "with",
                "duration": "4",
                "notes": [
                    16
                ]
            },
            {
                "lyrics": "",
                "duration": "4",
                "notes": [
                    14
                ]
            },
            {
                "lyrics": "anthems",
                "duration": "16",
                "notes": [
                    12,
                    10,
                    14,
                    5
                ]
            },
            {
                "lyrics": "",
                "duration": "8",
                "notes": [
                    9
                ]
            },
            {
                "lyrics": "sweet",
                "duration": "12",
                "notes": [
                    5,
                    7,
                    10,
                    14
                ]
            },
            {
                "lyrics": "",
                "duration": "4",
                "notes": [
                    7
                ]
            },
            {
                "lyrics": "",
                "duration": -1,
                "notes": []
            },
            {
                "lyrics": "while",
                "duration": "4",
                "notes": [
                    9
                ]
            },
            {
                "lyrics": "shepherds",
                "duration": "12",
                "notes": [
                    10,
                    12,
                    3,
                    7
                ]
            },
            {
                "lyrics": "",
                "duration": "4",
                "notes": [
                    9
                ]
            },
            {
                "lyrics": "",
                "duration": "8",
                "notes": [
                    7,
                    8,
                    12,
                    3
                ]
            },
            {
                "lyrics": "watch",
                "duration": "16",
                "notes": [
                    6
                ]
            },
            {
                "lyrics": "",
                "duration": "4",
                "notes": [
                    4
                ]
            },
            {
                "lyrics": "are",
                "duration": "4",
                "notes": [
                    6
                ]
            },
            {
                "lyrics": "keeping?",
                "duration": "24",
                "notes": [
                    7
                ]
            },
            {
                "lyrics": "",
                "duration": "24",
                "notes": [
                    7
                ]
            }
        ],
        "id": 1
    }
]